llavaction/__init__.py
llavaction/constants.py
llavaction/conversation.py
llavaction/mm_utils.py
llavaction/utils.py
llavaction/action/benchmark.py
llavaction/action/chatgpt_utils.py
llavaction/action/dataset.py
llavaction/action/ek_eval.py
llavaction/action/generate_description.py
llavaction/action/generate_interval_pred.py
llavaction/action/generate_temporal_detection_data.py
llavaction/action/llava_inference.py
llavaction/action/make_visualizations.py
llavaction/action/prediction_analysis.py
llavaction/action/render_utils.py
llavaction/action/selective_inference.py
llavaction/action/utils.py
llavaction/action/vis_utils.py
llavaction/eval/evaluate_interleave.py
llavaction/eval/model_vqa.py
llavaction/model/__init__.py
llavaction/model/apply_delta.py
llavaction/model/builder.py
llavaction/model/consolidate.py
llavaction/model/llava_arch.py
llavaction/model/make_delta.py
llavaction/model/utils.py
llavaction/model/language_model/llava_gemma.py
llavaction/model/language_model/llava_llama.py
llavaction/model/language_model/llava_mistral.py
llavaction/model/language_model/llava_mixtral.py
llavaction/model/language_model/llava_mpt.py
llavaction/model/language_model/llava_qwen.py
llavaction/model/language_model/llava_qwen_moe.py
llavaction/model/language_model/modeling_llama.py
llavaction/model/multimodal_encoder/builder.py
llavaction/model/multimodal_encoder/clip_encoder.py
llavaction/model/multimodal_encoder/hf_vision.py
llavaction/model/multimodal_encoder/imagebind.py
llavaction/model/multimodal_encoder/open_clip_encoder.py
llavaction/model/multimodal_encoder/siglip_encoder.py
llavaction/model/multimodal_encoder/dev_eva_clip/eva_vit.py
llavaction/model/multimodal_encoder/dev_eva_clip/eva_clip/__init__.py
llavaction/model/multimodal_encoder/dev_eva_clip/eva_clip/constants.py
llavaction/model/multimodal_encoder/dev_eva_clip/eva_clip/eva_vit_model.py
llavaction/model/multimodal_encoder/dev_eva_clip/eva_clip/factory.py
llavaction-0.0.1.dist-info/licenses/LICENSE.md
llavaction-0.0.1.dist-info/METADATA
llavaction-0.0.1.dist-info/WHEEL
llavaction-0.0.1.dist-info/top_level.txt
llavaction-0.0.1.dist-info/RECORD
