Metadata-Version: 2.4
Name: llavaction
Version: 0.0.1
Summary: LLaVAction: Evaluating and Training Multi-Modal Large Language Models for Action Recognition
Classifier: Programming Language :: Python :: 3
Classifier: License :: OSI Approved :: Apache Software License
Requires-Python: >=3.8
License-File: LICENSE.md
Provides-Extra: standalone
Requires-Dist: shortuuid; extra == "standalone"
Requires-Dist: httpx==0.24.0; extra == "standalone"
Requires-Dist: einops; extra == "standalone"
Requires-Dist: ftfy; extra == "standalone"
Provides-Extra: train
Requires-Dist: llavaction[standalone]; extra == "train"
Requires-Dist: open_clip_torch; extra == "train"
Requires-Dist: fastapi; extra == "train"
Requires-Dist: markdown2[all]; extra == "train"
Requires-Dist: numpy; extra == "train"
Requires-Dist: requests; extra == "train"
Requires-Dist: sentencepiece; extra == "train"
Requires-Dist: uvicorn; extra == "train"
Requires-Dist: wandb; extra == "train"
Requires-Dist: deepspeed==0.14.4; extra == "train"
Requires-Dist: peft==0.4.0; extra == "train"
Requires-Dist: bitsandbytes==0.41.0; extra == "train"
Requires-Dist: einops==0.6.1; extra == "train"
Requires-Dist: einops-exts==0.0.4; extra == "train"
Requires-Dist: gradio_client==0.2.9; extra == "train"
Requires-Dist: urllib3<=2.0.0; extra == "train"
Requires-Dist: pydantic==1.10.8; extra == "train"
Requires-Dist: hf_transfer; extra == "train"
Requires-Dist: opencv-python; extra == "train"
Requires-Dist: av; extra == "train"
Requires-Dist: decord; extra == "train"
Requires-Dist: tyro; extra == "train"
Requires-Dist: scipy; extra == "train"
Dynamic: license-file
